bmlt/__init__.py
bmlt/common/__init__.py
bmlt/common/lmdb_storage.py
bmlt/py.typed
bmlt/tabular/__init__.py
bmlt/tabular/data/__init__.py
bmlt/tabular/data/dataset.py
bmlt-0.1.0.dist-info/LICENSE
bmlt-0.1.0.dist-info/WHEEL
bmlt-0.1.0.dist-info/METADATA
bmlt-0.1.0.dist-info/RECORD
