Metadata-Version: 2.1
Name: bmlt
Version: 0.1.0
Summary: Some useful machine learning tools
Home-page: https://github.com/ilbumi/bmlt
License: MIT
Author: Ilya Bushmakin
Author-email: im.bushmakin@gmail.com
Requires-Python: >=3.7,<4.0
Classifier: Development Status :: 2 - Pre-Alpha
Classifier: Intended Audience :: Developers
Classifier: License :: OSI Approved :: MIT License
Classifier: Natural Language :: English
Classifier: Operating System :: OS Independent
Classifier: Programming Language :: Python :: 3
Classifier: Programming Language :: Python :: 3.7
Classifier: Programming Language :: Python :: 3.8
Classifier: Programming Language :: Python :: 3.9
Classifier: Programming Language :: Python :: 3.10
Classifier: Programming Language :: Python :: 3.11
Classifier: Topic :: Software Development :: Libraries
Requires-Dist: lmdbm (>=0.0.5,<0.0.6)
Requires-Dist: torch (>=1.13.0,<2.0.0)
Project-URL: Bug Tracker, https://github.com/ilbumi/bmlt/issues
Project-URL: Changelog, https://github.com/ilbumi/bmlt/blob/main/CHANGELOG.md
Project-URL: Documentation, https://bmlt.readthedocs.io
Project-URL: Repository, https://github.com/ilbumi/bmlt
